rosetta_service_monitor/__init__.py
rosetta_service_monitor/client/__init__.py
rosetta_service_monitor/client/conf.py
rosetta_service_monitor/client/enums.py
rosetta_service_monitor/client/fastapi_hook.py
rosetta_service_monitor/client/fastapi_metrics_hook.py
rosetta_service_monitor/client/metrics_conf.py
rosetta_service_monitor/client/monitor.py
rosetta_service_monitor/client/service/__init__.py
rosetta_service_monitor/client/service/metrics_service.py
rosetta_service_monitor/client/service/mq_service.py
rosetta_service_monitor/tasks/__init__.py
rosetta_service_monitor/tasks/background_task.py
rosetta_service_monitor/tasks/baskground_task_actor.py
rosetta_service_monitor-0.2.4.dist-info/METADATA
rosetta_service_monitor-0.2.4.dist-info/WHEEL
rosetta_service_monitor-0.2.4.dist-info/top_level.txt
rosetta_service_monitor-0.2.4.dist-info/RECORD
