Metadata-Version: 2.1
Name: rosetta-service-monitor
Version: 0.2.4
Summary: service monitor data collect client
Home-page: UNKNOWN
Author: xialei
Author-email: xialei@joyy.sg
License: UNKNOWN
Platform: UNKNOWN
Classifier: Programming Language :: Python :: 3
Classifier: License :: OSI Approved :: MIT License
Classifier: Operating System :: OS Independent
Requires-Python: >=3.7
Requires-Dist: attrdict (>=2.0.1)
Requires-Dist: certifi (>=2021.5.30)
Requires-Dist: charset-normalizer (>=2.0.4)
Requires-Dist: click (>=7.1.2)
Requires-Dist: idna (>=3.2)
Requires-Dist: importlib-metadata (>=4.6.3)
Requires-Dist: kafka-python (>=2.0.1)
Requires-Dist: loguru (>=0.5.3)
Requires-Dist: python-dotenv (>=0.19.0)
Requires-Dist: requests (>=2.26.0)
Requires-Dist: six (>=1.16.0)
Requires-Dist: typing-extensions (>=3.10.0.0)
Requires-Dist: urllib3 (>=1.26.6)
Requires-Dist: zipp (>=3.5.0)
Requires-Dist: uvicorn (>=0.13.4)
Requires-Dist: fastapi (>=0.63.0)
Requires-Dist: aiohttp (>=3.8.0)
